globsters-0.0.3.dist-info/METADATA
globsters-0.0.3.dist-info/WHEEL
globsters/__init__.py
globsters/libglobsters.pyi
globsters/py.typed
globsters/libglobsters.pypy38-pp73-x86-linux-gnu.so
globsters-0.0.3.dist-info/RECORD
